embed_man/__init__.py
embed_man/embed_manager.py
embedman-2025.5.180914.dist-info/licenses/LICENSE
tests/__init__.py
tests/test_embed_manager.py
embedman-2025.5.180914.dist-info/METADATA
embedman-2025.5.180914.dist-info/WHEEL
embedman-2025.5.180914.dist-info/top_level.txt
embedman-2025.5.180914.dist-info/RECORD
